vibekit/__init__.py
vibekit/examples/README.md
vibekit/examples/accounting_example.py
vibekit/examples/biology_example.py
vibekit/examples/chemistry_example.py
vibekit/examples/data_analysis_example.py
vibekit/examples/interactive_physics_README.md
vibekit/examples/interactive_physics_example.py
vibekit/examples/law_example.py
vibekit/examples/physics_example.py
vibekit/examples/requirements.txt
vibekit/examples/simple_example.py
vibekit/vibekit/__init__.py
vibekit/vibekit/client.py
vibekit/vibekit/core/__init__.py
vibekit/vibekit/core/interpreter.py
vibekit/vibekit/utils/__init__.py
vibekit/vibekit/utils/async_utils.py
vibekit-0.1.0.dist-info/METADATA
vibekit-0.1.0.dist-info/WHEEL
vibekit-0.1.0.dist-info/RECORD
