Metadata-Version: 2.4
Name: vibekit
Version: 0.1.0
Summary: A dynamic, intent-driven Python library that interprets and executes functions based on your needs
Project-URL: Homepage, https://github.com/lswank/vibekit
Project-URL: Issues, https://github.com/lswank/vibekit/issues
Author-email: Lorenzo Swank <Lorenzo@LorenzoSwank.com>
License: MIT
Classifier: Development Status :: 3 - Alpha
Classifier: License :: OSI Approved :: MIT License
Classifier: Operating System :: OS Independent
Classifier: Programming Language :: Python :: 3
Classifier: Programming Language :: Python :: 3.9
Classifier: Programming Language :: Python :: 3.10
Classifier: Programming Language :: Python :: 3.11
Classifier: Topic :: Software Development :: Libraries
Requires-Python: >=3.9
Requires-Dist: aiohttp>=3.8.0
Requires-Dist: anthropic>=0.5.0
Requires-Dist: openai>=1.0.0
Provides-Extra: dev
Requires-Dist: black>=23.0.0; extra == 'dev'
Requires-Dist: isort>=5.12.0; extra == 'dev'
Requires-Dist: mypy>=1.0.0; extra == 'dev'
Requires-Dist: pytest-asyncio>=0.21.0; extra == 'dev'
Requires-Dist: pytest>=7.0.0; extra == 'dev'
